{"controlador.ed.lista.ListaEnlazada":{"cabecera":{"info":{"@class":"modelo.Manga","id":1,"titulo":"Dragon Ball","id_autor":1,"id_editorial":1,"numPaginas":20,"tomo":1},"sig":{"info":{"@class":"modelo.Manga","id":2,"titulo":"AstroBoy","id_autor":2,"id_editorial":2,"numPaginas":20,"tomo":1},"sig":{"info":{"@class":"modelo.Manga","id":3,"titulo":"One Piece","id_autor":3,"id_editorial":3,"numPaginas":50,"tomo":1},"sig":{"info":{"@class":"modelo.Manga","id":4,"titulo":"Naruto","id_autor":4,"id_editorial":1,"numPaginas":20,"tomo":1},"sig":{"info":{"@class":"modelo.Manga","id":5,"titulo":"JOJOs","id_autor":6,"id_editorial":2,"numPaginas":20,"tomo":1},"sig":{"info":{"@class":"modelo.Manga","id":6,"titulo":"Chobit","id_autor":1,"id_editorial":2,"numPaginas":15,"tomo":15},"sig":{"info":{"@class":"modelo.Manga","id":7,"titulo":"Uzumaki","id_autor":8,"id_editorial":5,"numPaginas":20,"tomo":20},"sig":{"info":{"@class":"modelo.Manga","id":8,"titulo":"BUenas noches PunPun","id_autor":9,"id_editorial":6,"numPaginas":224,"tomo":224},"sig":{"info":{"@class":"modelo.Manga","id":9,"titulo":"Viland Saga","id_autor":10,"id_editorial":7,"numPaginas":20,"tomo":20}}}}}}}}}},"size":9}}